eyes3scribe/DocSectionWriterFunction.py
eyes3scribe/__init__.py
eyes3scribe/config.py
eyes3scribe/function_call_tree.py
eyes3scribe/function_dependency_processor.py
eyes3scribe/gen_handwritten_docs.py
eyes3scribe/gen_mkdocs_nav_bar.py
eyes3scribe/gen_pynavbar_dict.py
eyes3scribe/helpo/__init__.py
eyes3scribe/helpo/coloured_log_formatter.py
eyes3scribe/helpo/hcollections.py
eyes3scribe/helpo/hdatetime.py
eyes3scribe/helpo/hfile.py
eyes3scribe/helpo/hstrops.py
eyes3scribe/helpo/hsubprocess.py
eyes3scribe/helpo/old/hfile.py
eyes3scribe/helpo/old/hstrops.py
eyes3scribe/helpo/old/hsubprocess.py
eyes3scribe/launcher.py
eyes3scribe/models/__init__.py
eyes3scribe/models/filepath_datahandler.py
eyes3scribe/models/function_datahandler.py
eyes3scribe/models/mdfile_datahandler.py
eyes3scribe/models/rst2md_datahandler.py
eyes3scribe/pipeline_rst2md.py
eyes3scribe/regex_patterns.py
eyes3scribe/rst2md_converters/__init__.py
eyes3scribe/rst2md_converters/r2m_anchors_end_step1.py
eyes3scribe/rst2md_converters/r2m_anchors_start_step2.py
eyes3scribe/rst2md_converters/r2m_triple_colonic_bypass.py
eyes3scribe/setup_docs_project.py
eyes3scribe/shell_2md_file_writer.py
eyes3scribe/shell_src_preprocessor.py
eyes3scribe-0.2.0.dist-info/LICENSE
eyes3scribe-0.2.0.dist-info/METADATA
eyes3scribe-0.2.0.dist-info/WHEEL
eyes3scribe-0.2.0.dist-info/RECORD
