Metadata-Version: 2.1
Name: eyes3scribe
Version: 0.2.0
Summary: Automatically creates HTML documentation files for BASH/Shell source code using markdown & python mkdocs
Home-page: https://github.com/stablecaps/eyes3scribe
License: Apache Software License 2.0
Keywords: shell,html,bash,markdown,documentation,automation,pandoc,sphinx,documentation-tool,mkdocs,python3,website-builder,website-generation,shell-script,markdown-to-html,rst,auto-documentation
Author: Stablecaps
Author-email: 14529342+darkpandarts@users.noreply.github.com
Requires-Python: >=3.9,<4.0
Classifier: Development Status :: 2 - Pre-Alpha
Classifier: Intended Audience :: Developers
Classifier: License :: OSI Approved :: Apache Software License
Classifier: License :: Other/Proprietary License
Classifier: Operating System :: POSIX :: Linux
Classifier: Programming Language :: Python :: 3
Classifier: Programming Language :: Python :: 3.9
Classifier: Programming Language :: Python :: 3.10
Classifier: Programming Language :: Python :: 3.11
Classifier: Programming Language :: Python :: 3.12
Classifier: Topic :: Software Development :: Libraries :: Python Modules
Requires-Dist: build (>=1.0.3,<2.0.0)
Requires-Dist: wheel (>=0.42.0,<0.43.0)
Project-URL: Bug Tracker, https://github.com/stablecaps/eyes3scribe/issues
Project-URL: Repository, https://github.com/stablecaps/eyes3scribe
